{
	"$schema": "http://schema.management.azure.com/schemas/2015-01-01/deploymentTemplate.json#",
	"contentVersion": "1.0.0.0",
	"parameters": {
		"factoryName": {
			"type": "string",
			"metadata": "Data Factory name",
			"defaultValue": "davidADF123"
		},
		"AzureDataLakeStorage1_accountKey": {
			"type": "secureString",
			"metadata": "Secure string for 'accountKey' of 'AzureDataLakeStorage1'"
		},
		"AzureSqlDatabase1_connectionString": {
			"type": "secureString",
			"metadata": "Secure string for 'connectionString' of 'AzureSqlDatabase1'"
		},
		"DavidAzureBlobStorage1_connectionString": {
			"type": "secureString",
			"metadata": "Secure string for 'connectionString' of 'DavidAzureBlobStorage1'"
		},
		"DavidAzureDataLakeConnection_accountKey": {
			"type": "secureString",
			"metadata": "Secure string for 'accountKey' of 'DavidAzureDataLakeConnection'"
		},
		"HttpServer1_password": {
			"type": "secureString",
			"metadata": "Secure string for 'password' of 'HttpServer1'"
		},
		"AzureDataLakeStorage1_properties_typeProperties_url": {
			"type": "string",
			"defaultValue": "https://davidgen2datalake1.dfs.core.windows.net/"
		},
		"DavidAzureDataLakeConnection_properties_typeProperties_url": {
			"type": "string",
			"defaultValue": "https://daviddatagen2lake.dfs.core.windows.net/"
		},
		"HTTP_Rebrickable_properties_typeProperties_url": {
			"type": "string",
			"defaultValue": "https://cdn.rebrickable.com/media/downloads/"
		},
		"HttpServer1_properties_typeProperties_url": {
			"type": "string",
			"defaultValue": "https://api.open-meteo.com/v1/forecast?latitude=52.52&longitude=13.41&hourly=temperature_2m&daily=temperature_2m_max,temperature_2m_min,sunrise,sunset&timezone=GMT"
		},
		"HttpServer1_properties_typeProperties_userName": {
			"type": "string",
			"defaultValue": "serverAdmin123"
		},
		"containerUri": {
			"type": "string",
			"metadata": "URI to storage account containing linked ARM templates"
		},
		"containerSasToken": {
			"type": "string",
			"metadata": "Sas token to storage account containing linked ARM templates"
		}
	},
	"variables": {
		"factoryId": "[concat('Microsoft.DataFactory/factories/', parameters('factoryName'))]"
	},
	"resources": [
		{
			"name": "davidADF123_ArmTemplate_0",
			"type": "Microsoft.Resources/deployments",
			"apiVersion": "2018-02-01",
			"properties": {
				"mode": "incremental",
				"templateLink": {
					"uri": "[concat(parameters('containerUri'), '/ArmTemplate_0.json', parameters('containerSasToken'))]",
					"contentVersion": "1.0.0.0"
				},
				"parameters": {
					"factoryName": {
						"value": "[parameters('factoryName')]"
					},
					"AzureDataLakeStorage1_accountKey": {
						"value": "[parameters('AzureDataLakeStorage1_accountKey')]"
					},
					"AzureSqlDatabase1_connectionString": {
						"value": "[parameters('AzureSqlDatabase1_connectionString')]"
					},
					"DavidAzureDataLakeConnection_accountKey": {
						"value": "[parameters('DavidAzureDataLakeConnection_accountKey')]"
					},
					"HttpServer1_password": {
						"value": "[parameters('HttpServer1_password')]"
					},
					"DavidAzureBlobStorage1_connectionString": {
						"value": "[parameters('DavidAzureBlobStorage1_connectionString')]"
					},
					"AzureDataLakeStorage1_properties_typeProperties_url": {
						"value": "[parameters('AzureDataLakeStorage1_properties_typeProperties_url')]"
					},
					"DavidAzureDataLakeConnection_properties_typeProperties_url": {
						"value": "[parameters('DavidAzureDataLakeConnection_properties_typeProperties_url')]"
					},
					"HTTP_Rebrickable_properties_typeProperties_url": {
						"value": "[parameters('HTTP_Rebrickable_properties_typeProperties_url')]"
					},
					"HttpServer1_properties_typeProperties_url": {
						"value": "[parameters('HttpServer1_properties_typeProperties_url')]"
					},
					"HttpServer1_properties_typeProperties_userName": {
						"value": "[parameters('HttpServer1_properties_typeProperties_userName')]"
					}
				}
			},
			"dependsOn": []
		}
	]
}